UART/UART_vsc_state/uart_tx.v
// Moore型三段式状态机实现uart发送模块
/*
一帧bus_in数据的存在时间必须不小于一个clk_baud周期,且不大于12个clk_baud周期才能正确传输。

clk_baud:_/ 1\__/ 2\__/ 3\__······__/11\__/12\__/13\_
bus_in:  _/xx/¯¯¯¯¯¯¯¯¯¯¯¯¯¯······¯¯¯¯¯¯¯¯¯¯¯\xxxx\__

过短时，状态机无法进入下一状态去发送数据；过长时，状态机会重复发送这一帧数据。
可以通过修改bus_arrival参数的生成逻辑来解决，这里忽略这个问题。
*/
module uart_tx_moore (
    input rst,  // 异步复位信号（高电平有效）
    input clk_baud,  // 波特率时钟
    input [7:0] bus_in,  // 输入总线
    output reg serial_out  // 串行输出
);

    // 状态寄存器
    reg [3:0] current_state;  // 当前状态
    reg [3:0] next_state;  // 下一状态
    // 数据寄存器
    reg [7:0] bus_buff;
    reg parity_even;

    wire bus_arrival;

    // 状态码
    localparam 
    state_0 = 4'b0000,  state_1 = 4'b0001,  state_2 = 4'b0010,
    state_3 = 4'b0011,  state_4 = 4'b0100,  state_5 = 4'b0101,
    state_6 = 4'b0110,  state_7 = 4'b0111,  state_8 = 4'b1000,
    state_9 = 4'b1001,  state_10= 4'b1010,  state_11= 4'b1011; 


    // 如何判断总线数据到来？
    // 我的思路是非全零时表示总线数据到来
    assign bus_arrival = | bus_in;
    always @(*) begin
        if (rst)  
            bus_buff = 8'b0;
        else begin
            // 在空闲状态获取总线数据，
            if(current_state == state_0) begin
                if(bus_arrival)  begin
                    bus_buff = bus_in;                  
                    parity_even = ^ bus_buff;  // 偶校验
                end 
                else begin
                    bus_buff = 8'b0;
                    parity_even = 1'b0;
                end
            end
            // 在其他状态保持缓存的总线数据，不需要else语句
        end
    end

////////////////////////三段式状态机///////////////////////////


    // 时序逻辑部分（当前状态）
    always @(posedge clk_baud, posedge rst) begin
        if(rst) begin
            current_state <= state_0; 
        end
        else begin
            current_state <= next_state;
        end    
    end


    // 组合逻辑部分（状态转换）
    always @(*) begin
        next_state = state_0;
        case (current_state)
            state_0 : begin  // 等待状态
                    if(bus_arrival) 
                        next_state = state_1;
                    else
                        next_state = state_0;
                    end
            state_1 : begin  // 起始位发送状态
                    next_state = state_2;
                    end
            state_2 : begin
                    next_state = state_3;
                    end
            state_3 : begin
                    next_state = state_4;
                    end
            state_4 : begin
                    next_state = state_5;
                    end
            state_5 : begin
                    next_state = state_6;
                    end
            state_6 : begin
                    next_state = state_7;
                    end
            state_7 : begin
                    next_state = state_8;
                    end
            state_8 : begin
                    next_state = state_9;
                    end
            state_9 : begin
                    next_state = state_10;
                    end
            state_10 : begin
                    next_state = state_11;
                    end
            state_11 : begin
                    next_state = state_0;
                    end        
            default: next_state = state_0;
        endcase    
    end


    // 组合逻辑部分（输出）
    always @(*) begin
        if(rst) 
            serial_out = 1'b1;
        else begin
            case (current_state) 
                state_0 : serial_out = 1'b1;
                state_1 : serial_out = 1'b0;
                state_2 : serial_out = bus_buff[7];
                state_3 : serial_out = bus_buff[6];
                state_4 : serial_out = bus_buff[5];
                state_5 : serial_out = bus_buff[4];
                state_6 : serial_out = bus_buff[3];
                state_7 : serial_out = bus_buff[2];
                state_8 : serial_out = bus_buff[1];
                state_9 : serial_out = bus_buff[0];
                state_10: serial_out = parity_even;
                state_11: serial_out = 1'b1;
                default: serial_out = 1'b1;
            endcase
        end
                
    end

///////////////////////////////////////////////////////////////

endmodule

UART/UART_vsc_state/tb_tx.v
`timescale 1ns/1ps
`include "uart_tx.v"
/*
uart_tx模块测试文件
波特率9600，T=104166.6ns
rst复位高电平有效
*/
module tb_tx ();

    //localparam T = 104166;
    localparam T = 16;

    reg rst;
    reg clk_baud;
    reg [7:0] bus_in;

    wire serial_out;

    initial begin
        rst = 1'b0;
        clk_baud = 1'b0;
        bus_in = 8'b0;
    end

    initial begin
        repeat(2*50)
        #(T/2)  clk_baud = ~clk_baud;
    end

    initial begin
        rst = 1'b1;  #T  // 1
        rst = 1'b0;  #(T*23)
        rst = 1'b0;  #T  // 25
        rst = 1'b0;
    end

    initial begin
        bus_in = 8'b0;  #(T*4)
        bus_in = 8'b10011001;  #(1.5*T)  // 5
        bus_in = 8'b0;  #(T*11)
        bus_in = 8'b0;  #(T*3) 
        bus_in = 8'b01100010;  #T  // 20
        bus_in = 8'b0;
    end

    uart_tx_moore     tb_tx_ins(
        .rst            (rst),
        .clk_baud       (clk_baud),
        .bus_in         (bus_in),
        .serial_out     (serial_out)
    );

    initial begin
        $dumpfile("wave_tx.vcd");
        $dumpvars(0,tb_tx);
    end

endmodule

UART/UART_vsc_state/wave_tx.vcd
$date
	Wed Jun 15 21:11:18 2022
$end
$version
	Icarus Verilog
$end
$timescale
	1ps
$end
$scope module tb_tx $end
$var wire 1 ! serial_out $end
$var reg 8 " bus_in [7:0] $end
$var reg 1 # clk_baud $end
$var reg 1 $ rst $end
$scope module tb_tx_ins $end
$var wire 8 % bus_in [7:0] $end
$var wire 1 # clk_baud $end
$var wire 1 $ rst $end
$var wire 1 & bus_arrival $end
$var reg 8 ' bus_buff [7:0] $end
$var reg 4 ( current_state [3:0] $end
$var reg 4 ) next_state [3:0] $end
$var reg 1 * parity_even $end
$var reg 1 ! serial_out $end
$upscope $end
$upscope $end
$enddefinitions $end
#0
$dumpvars
x*
b0 )
b0 (
b0 '
0&
b0 %
1$
0#
b0 "
1!
$end
#8000
1#
#16000
0*
0#
0$
#24000
1#
#32000
0#
#40000
1#
#48000
0#
#56000
1#
#64000
b1 )
b10011001 '
0#
1&
b10011001 "
b10011001 %
#72000
0!
b10 )
b1 (
1#
#80000
0#
#88000
1!
b10 (
b11 )
1#
0&
b0 "
b0 %
#96000
0#
#104000
0!
b100 )
b11 (
1#
#112000
0#
#120000
b101 )
b100 (
1#
#128000
0#
#136000
1!
b110 )
b101 (
1#
#144000
0#
#152000
b111 )
b110 (
1#
#160000
0#
#168000
0!
b1000 )
b111 (
1#
#176000
0#
#184000
b1001 )
b1000 (
1#
#192000
0#
#200000
1!
b1010 )
b1001 (
1#
#208000
0#
#216000
0!
b1011 )
b1010 (
1#
#224000
0#
#232000
1!
b0 )
b1011 (
1#
#240000
0#
#248000
b0 '
b0 (
1#
#256000
0#
#264000
1#
#272000
0#
#280000
1#
#288000
0#
#296000
1#
#304000
0#
#312000
0!
b1 (
b10 )
1*
b1100010 '
1#
1&
b1100010 "
b1100010 %
#320000
0#
#328000
b10 (
b11 )
1#
0&
b0 "
b0 %
#336000
0#
#344000
1!
b100 )
b11 (
1#
#352000
0#
#360000
b101 )
b100 (
1#
#368000
0#
#376000
0!
b110 )
b101 (
1#
#384000
0#
#392000
b111 )
b110 (
1#
#400000
0#
#408000
b1000 )
b111 (
1#
#416000
0#
#424000
1!
b1001 )
b1000 (
1#
#432000
0#
#440000
0!
b1010 )
b1001 (
1#
#448000
0#
#456000
1!
b1011 )
b1010 (
1#
#464000
0#
#472000
b0 )
b1011 (
1#
#480000
0#
#488000
0*
b0 '
b0 (
1#
