UART/UART_vsc_state/uart_rx.v
// 状态机实现接收

module uart_rx_moore (
    input rst,
    input clk_baud,
    input clk_sample,
    input serial_in,
    output reg [7:0] bus_out
);

    // 状态寄存器
    reg [3:0] current_state;
    reg [3:0] next_state;
    // 并行数据缓存器
    reg [8:0] bus_buff;
    // 采样数据缓存
    reg signal_sample;
    // 校验指示
    reg parity_ture;
    // 采样点数
    reg [3:0] cnt_sample;

    // 接收指示
    reg serial_arrival; 

    // 接收机状态码
    localparam 
    state_0 = 4'b0000,  state_1 = 4'b0001,  state_2 = 4'b0010,
    state_3 = 4'b0011,  state_4 = 4'b0100,  state_5 = 4'b0101,
    state_6 = 4'b0110,  state_7 = 4'b0111,  state_8 = 4'b1000,
    state_9 = 4'b1001,  state_10= 4'b1010,  state_11= 4'b1011; 


    // 采样机
    always @(posedge clk_sample, posedge rst) begin
        if(rst) begin
            serial_arrival <= 1'b0;
            cnt_sample <= 4'b0;
            signal_sample <= 1'b0;
        end
        else begin
            // 在空闲状态寻找起始位
            if(current_state == state_0) begin
                case (serial_in)
                    1'b0 :  begin  // 出现低电平
                        // 8进制计数
                        if(cnt_sample == 4'b0111) begin
                            cnt_sample <= 4'b0;
                            serial_arrival <= 1'b1;
                        end
                        else begin
                            cnt_sample <= cnt_sample + 4'b1;
                        end
                    end
                    default : cnt_sample <= 4'b0;
                endcase
            end
            // 在接收状态对信号采样
            else begin
                serial_arrival <= 1'b0;
                // 16进制计数
                 if(cnt_sample == 4'b1111) begin
                    signal_sample <= serial_in;
                    cnt_sample <= 4'b0;
                 end
                 else begin
                     cnt_sample <= cnt_sample + 4'b1;
                 end   
            end 
        end
        
    end

////////////////////////接收状态机(三段式)///////////////////////////


    // 时序逻辑部分（当前状态）
    always @(posedge clk_baud, posedge rst) begin
        if(rst) begin
            current_state <= state_0; 
        end
        else begin
            current_state <= next_state;
        end    
    end


    // 组合逻辑部分（状态转换）
    always @(*) begin
        next_state = state_0;
        case (current_state)
            state_0 : begin
                    if (serial_arrival) begin
                        next_state <= state_1;
                    end
                    else 
                        next_state <= state_0;
                    end
            state_1 : begin  // 接收第一位
                    next_state = state_2;
                    end
            state_2 : begin
                    next_state = state_3;
                    end
            state_3 : begin
                    next_state = state_4;
                    end
            state_4 : begin
                    next_state = state_5;
                    end
            state_5 : begin
                    next_state = state_6;
                    end
            state_6 : begin
                    next_state = state_7;
                    end
            state_7 : begin
                    next_state = state_8;
                    end
            state_8 : begin
                    next_state = state_9;
                    end
            state_9 : begin 
                    next_state = state_10;
                    end
            state_10 : begin 
                    next_state = state_11;
                    end 
            state_11 : begin
                    next_state = state_0;
                    end        
            default: next_state = state_0;
        endcase    
    end


    // 组合逻辑部分（输出）
    always @(*) begin
        if(rst) 
            bus_out = 8'b0;
        else begin
            case (current_state) 
                state_0 : begin 
                          bus_buff = 9'b0;
                          bus_out = 8'b0;
                end
                state_1 : bus_buff[8] = signal_sample;
                state_2 : bus_buff[7] = signal_sample;
                state_3 : bus_buff[6] = signal_sample;
                state_4 : bus_buff[5] = signal_sample;
                state_5 : bus_buff[4] = signal_sample;
                state_6 : bus_buff[3] = signal_sample;
                state_7 : bus_buff[2] = signal_sample;
                state_8 : bus_buff[1] = signal_sample;
                state_9 : bus_buff[0] = signal_sample;
                state_10: begin  // 数据校验
                          if(bus_buff[0] != ^bus_buff[8:1])
                                bus_buff = 9'b0;
                          end
                state_11: bus_out = bus_buff[8:1];
                default: current_state = state_0;
            endcase
        end
                
    end
 
/////////////////////////////////////////////////////////////////
endmodule

UART/UART_vsc_state/tb_rx.v
`timescale 1ns/1ps
`include "uart_rx.v"

module tb_rx ();

    parameter t = 2;
    parameter T = 32;

    reg rst;
    reg clk_baud;
    reg clk_sample;
    reg serial_in;

    wire [7:0] bus_out;

    initial begin
        rst = 0;
        clk_baud = 0;
        clk_sample = 0;
        serial_in = 0;
    end

    initial begin
        rst = 1'b1;  #t
        rst = 1'b0; 
    end

    initial begin
        repeat(100)  
        #(T/2)  clk_baud = ~clk_baud;
    end

    initial begin
        repeat(1600)
        #(t/2)  clk_sample = ~clk_sample;
    end

    //0_10011001_0_1
    //0_11000010_0_1错误校验
    initial begin
        serial_in = 1'b1; #(T*2)

        serial_in = 1'b 0 ;  #T
        serial_in = 1'b 1 ;  #T
        serial_in = 1'b 0 ;  #T
        serial_in = 1'b 0 ;  #T
        serial_in = 1'b 1 ;  #T
        serial_in = 1'b 1 ;  #T
        serial_in = 1'b 0 ;  #T
        serial_in = 1'b 0 ;  #T
        serial_in = 1'b 1 ;  #T
        serial_in = 1'b 0 ;  #T
        serial_in = 1'b 1 ;  #T

        serial_in = 1'b1; #(T*2)

        serial_in = 1'b 0 ;  #T
        serial_in = 1'b 1 ;  #T
        serial_in = 1'b 1 ;  #T
        serial_in = 1'b 0 ;  #T
        serial_in = 1'b 0 ;  #T
        serial_in = 1'b 0 ;  #T
        serial_in = 1'b 0 ;  #T
        serial_in = 1'b 1 ;  #T
        serial_in = 1'b 0 ;  #T
        serial_in = 1'b 0 ;  #T  // 错误校验位
        serial_in = 1'b 1 ;  #T

        serial_in = 1'b1;
    end

    uart_rx_moore    tb_rx_ins(
        .rst        (rst),
        .clk_baud   (clk_baud),
        .clk_sample (clk_sample),
        .serial_in  (serial_in),
        .bus_out    (bus_out)
    );

    initial begin
        $dumpfile("wave_rx.vcd");
        $dumpvars(0, tb_rx);
    end


endmodule

UART/UART_vsc_state/wave_rx.vcd
$date
	Wed Jun 15 21:12:36 2022
$end
$version
	Icarus Verilog
$end
$timescale
	1ps
$end
$scope module tb_rx $end
$var wire 8 ! bus_out [7:0] $end
$var reg 1 " clk_baud $end
$var reg 1 # clk_sample $end
$var reg 1 $ rst $end
$var reg 1 % serial_in $end
$scope module tb_rx_ins $end
$var wire 1 " clk_baud $end
$var wire 1 # clk_sample $end
$var wire 1 $ rst $end
$var wire 1 % serial_in $end
$var reg 9 & bus_buff [8:0] $end
$var reg 8 ' bus_out [7:0] $end
$var reg 4 ( cnt_sample [3:0] $end
$var reg 4 ) current_state [3:0] $end
$var reg 4 * next_state [3:0] $end
$var reg 1 + serial_arrival $end
$var reg 1 , signal_sample $end
$upscope $end
$upscope $end
$enddefinitions $end
#0
$dumpvars
0,
0+
b0 *
b0 )
b0 (
b0 '
bx &
1%
1$
0#
0"
b0 !
$end
#1000
1#
#2000
b0 &
0#
0$
#3000
1#
#4000
0#
#5000
1#
#6000
0#
#7000
1#
#8000
0#
#9000
1#
#10000
0#
#11000
1#
#12000
0#
#13000
1#
#14000
0#
#15000
1#
#16000
0#
1"
#17000
1#
#18000
0#
#19000
1#
#20000
0#
#21000
1#
#22000
0#
#23000
1#
#24000
0#
#25000
1#
#26000
0#
#27000
1#
#28000
0#
#29000
1#
#30000
0#
#31000
1#
#32000
0#
0"
#33000
1#
#34000
0#
#35000
1#
#36000
0#
#37000
1#
#38000
0#
#39000
1#
#40000
0#
#41000
1#
#42000
0#
#43000
1#
#44000
0#
#45000
1#
#46000
0#
#47000
1#
#48000
0#
1"
#49000
1#
#50000
0#
#51000
1#
#52000
0#
#53000
1#
#54000
0#
#55000
1#
#56000
0#
#57000
1#
#58000
0#
#59000
1#
#60000
0#
#61000
1#
#62000
0#
#63000
1#
#64000
0#
0"
0%
#65000
b1 (
1#
#66000
0#
#67000
b10 (
1#
#68000
0#
#69000
b11 (
1#
#70000
0#
#71000
b100 (
1#
#72000
0#
#73000
b101 (
1#
#74000
0#
#75000
b110 (
1#
#76000
0#
#77000
b111 (
1#
#78000
0#
#79000
b1 *
1+
b0 (
1#
#80000
b10 *
b1 )
0#
1"
#81000
b10 *
b1 (
0+
1#
#82000
0#
#83000
b10 (
1#
#84000
0#
#85000
b11 (
1#
#86000
0#
#87000
b100 (
1#
#88000
0#
#89000
b101 (
1#
#90000
0#
#91000
b110 (
1#
#92000
0#
#93000
b111 (
1#
#94000
0#
#95000
b1000 (
1#
#96000
0#
0"
1%
#97000
b1001 (
1#
#98000
0#
#99000
b1010 (
1#
#100000
0#
#101000
b1011 (
1#
#102000
0#
#103000
b1100 (
1#
#104000
0#
#105000
b1101 (
1#
#106000
0#
#107000
b1110 (
1#
#108000
0#
#109000
b1111 (
1#
#110000
0#
#111000
b100000000 &
b0 (
1,
1#
#112000
b110000000 &
b11 *
b10 )
0#
1"
#113000
b1 (
1#
#114000
0#
#115000
b10 (
1#
#116000
0#
#117000
b11 (
1#
#118000
0#
#119000
b100 (
1#
#120000
0#
#121000
b101 (
1#
#122000
0#
#123000
b110 (
1#
#124000
0#
#125000
b111 (
1#
#126000
0#
#127000
b1000 (
1#
#128000
0#
0"
0%
#129000
b1001 (
1#
#130000
0#
#131000
b1010 (
1#
#132000
0#
#133000
b1011 (
1#
#134000
0#
#135000
b1100 (
1#
#136000
0#
#137000
b1101 (
1#
#138000
0#
#139000
b1110 (
1#
#140000
0#
#141000
b1111 (
1#
#142000
0#
#143000
b100000000 &
b0 (
0,
1#
#144000
b100 *
b11 )
0#
1"
#145000
b1 (
1#
#146000
0#
#147000
b10 (
1#
#148000
0#
#149000
b11 (
1#
#150000
0#
#151000
b100 (
1#
#152000
0#
#153000
b101 (
1#
#154000
0#
#155000
b110 (
1#
#156000
0#
#157000
b111 (
1#
#158000
0#
#159000
b1000 (
1#
#160000
0#
0"
#161000
b1001 (
1#
#162000
0#
#163000
b1010 (
1#
#164000
0#
#165000
b1011 (
1#
#166000
0#
#167000
b1100 (
1#
#168000
0#
#169000
b1101 (
1#
#170000
0#
#171000
b1110 (
1#
#172000
0#
#173000
b1111 (
1#
#174000
0#
#175000
b0 (
1#
#176000
b101 *
b100 )
0#
1"
#177000
b1 (
1#
#178000
0#
#179000
b10 (
1#
#180000
0#
#181000
b11 (
1#
#182000
0#
#183000
b100 (
1#
#184000
0#
#185000
b101 (
1#
#186000
0#
#187000
b110 (
1#
#188000
0#
#189000
b111 (
1#
#190000
0#
#191000
b1000 (
1#
#192000
0#
0"
1%
#193000
b1001 (
1#
#194000
0#
#195000
b1010 (
1#
#196000
0#
#197000
b1011 (
1#
#198000
0#
#199000
b1100 (
1#
#200000
0#
#201000
b1101 (
1#
#202000
0#
#203000
b1110 (
1#
#204000
0#
#205000
b1111 (
1#
#206000
0#
#207000
b100100000 &
b0 (
1,
1#
#208000
b100110000 &
b110 *
b101 )
0#
1"
#209000
b1 (
1#
#210000
0#
#211000
b10 (
1#
#212000
0#
#213000
b11 (
1#
#214000
0#
#215000
b100 (
1#
#216000
0#
#217000
b101 (
1#
#218000
0#
#219000
b110 (
1#
#220000
0#
#221000
b111 (
1#
#222000
0#
#223000
b1000 (
1#
#224000
0#
0"
#225000
b1001 (
1#
#226000
0#
#227000
b1010 (
1#
#228000
0#
#229000
b1011 (
1#
#230000
0#
#231000
b1100 (
1#
#232000
0#
#233000
b1101 (
1#
#234000
0#
#235000
b1110 (
1#
#236000
0#
#237000
b1111 (
1#
#238000
0#
#239000
b0 (
1#
#240000
b100111000 &
b111 *
b110 )
0#
1"
#241000
b1 (
1#
#242000
0#
#243000
b10 (
1#
#244000
0#
#245000
b11 (
1#
#246000
0#
#247000
b100 (
1#
#248000
0#
#249000
b101 (
1#
#250000
0#
#251000
b110 (
1#
#252000
0#
#253000
b111 (
1#
#254000
0#
#255000
b1000 (
1#
#256000
0#
0"
0%
#257000
b1001 (
1#
#258000
0#
#259000
b1010 (
1#
#260000
0#
#261000
b1011 (
1#
#262000
0#
#263000
b1100 (
1#
#264000
0#
#265000
b1101 (
1#
#266000
0#
#267000
b1110 (
1#
#268000
0#
#269000
b1111 (
1#
#270000
0#
#271000
b100110000 &
b0 (
0,
1#
#272000
b1000 *
b111 )
0#
1"
#273000
b1 (
1#
#274000
0#
#275000
b10 (
1#
#276000
0#
#277000
b11 (
1#
#278000
0#
#279000
b100 (
1#
#280000
0#
#281000
b101 (
1#
#282000
0#
#283000
b110 (
1#
#284000
0#
#285000
b111 (
1#
#286000
0#
#287000
b1000 (
1#
#288000
0#
0"
#289000
b1001 (
1#
#290000
0#
#291000
b1010 (
1#
#292000
0#
#293000
b1011 (
1#
#294000
0#
#295000
b1100 (
1#
#296000
0#
#297000
b1101 (
1#
#298000
0#
#299000
b1110 (
1#
#300000
0#
#301000
b1111 (
1#
#302000
0#
#303000
b0 (
1#
#304000
b1001 *
b1000 )
0#
1"
#305000
b1 (
1#
#306000
0#
#307000
b10 (
1#
#308000
0#
#309000
b11 (
1#
#310000
0#
#311000
b100 (
1#
#312000
0#
#313000
b101 (
1#
#314000
0#
#315000
b110 (
1#
#316000
0#
#317000
b111 (
1#
#318000
0#
#319000
b1000 (
1#
#320000
0#
0"
1%
#321000
b1001 (
1#
#322000
0#
#323000
b1010 (
1#
#324000
0#
#325000
b1011 (
1#
#326000
0#
#327000
b1100 (
1#
#328000
0#
#329000
b1101 (
1#
#330000
0#
#331000
b1110 (
1#
#332000
0#
#333000
b1111 (
1#
#334000
0#
#335000
b100110010 &
b0 (
1,
1#
#336000
b100110011 &
b1010 *
b1001 )
0#
1"
#337000
b1 (
1#
#338000
0#
#339000
b10 (
1#
#340000
0#
#341000
b11 (
1#
#342000
0#
#343000
b100 (
1#
#344000
0#
#345000
b101 (
1#
#346000
0#
#347000
b110 (
1#
#348000
0#
#349000
b111 (
1#
#350000
0#
#351000
b1000 (
1#
#352000
0#
0"
0%
#353000
b1001 (
1#
#354000
0#
#355000
b1010 (
1#
#356000
0#
#357000
b1011 (
1#
#358000
0#
#359000
b1100 (
1#
#360000
0#
#361000
b1101 (
1#
#362000
0#
#363000
b1110 (
1#
#364000
0#
#365000
b1111 (
1#
#366000
0#
#367000
b100110010 &
b0 (
0,
1#
#368000
b1011 *
b1010 )
0#
1"
#369000
b1 (
1#
#370000
0#
#371000
b10 (
1#
#372000
0#
#373000
b11 (
1#
#374000
0#
#375000
b100 (
1#
#376000
0#
#377000
b101 (
1#
#378000
0#
#379000
b110 (
1#
#380000
0#
#381000
b111 (
1#
#382000
0#
#383000
b1000 (
1#
#384000
0#
0"
1%
#385000
b1001 (
1#
#386000
0#
#387000
b1010 (
1#
#388000
0#
#389000
b1011 (
1#
#390000
0#
#391000
b1100 (
1#
#392000
0#
#393000
b1101 (
1#
#394000
0#
#395000
b1110 (
1#
#396000
0#
#397000
b1111 (
1#
#398000
0#
#399000
b0 (
1,
1#
#400000
b10011001 !
b10011001 '
b0 *
b1011 )
0#
1"
#401000
b1 (
1#
#402000
0#
#403000
b10 (
1#
#404000
0#
#405000
b11 (
1#
#406000
0#
#407000
b100 (
1#
#408000
0#
#409000
b101 (
1#
#410000
0#
#411000
b110 (
1#
#412000
0#
#413000
b111 (
1#
#414000
0#
#415000
b1000 (
1#
#416000
0#
0"
#417000
b1001 (
1#
#418000
0#
#419000
b1010 (
1#
#420000
0#
#421000
b1011 (
1#
#422000
0#
#423000
b1100 (
1#
#424000
0#
#425000
b1101 (
1#
#426000
0#
#427000
b1110 (
1#
#428000
0#
#429000
b1111 (
1#
#430000
0#
#431000
b0 (
1#
#432000
b0 !
b0 '
b0 &
b0 )
0#
1"
