UART/UART_vsc_state/uart_rx.v
// 状态机实现接收

module uart_rx_moore (
    input rst,
    input clk_baud,
    input clk_sample,
    input serial_in,
    output reg [7:0] bus_out
);

    // 状态寄存器
    reg [3:0] current_state;
    reg [3:0] next_state;
    // 并行数据缓存器
    reg [8:0] bus_buff;
    // 采样数据缓存
    reg signal_sample;
    // 校验指示
    reg parity_ture;
    // 采样点数
    reg [3:0] cnt_sample;

    // 接收指示
    reg serial_arrival; 

    // 接收机状态码
    localparam 
    state_0 = 4'b0000,  state_1 = 4'b0001,  state_2 = 4'b0010,
    state_3 = 4'b0011,  state_4 = 4'b0100,  state_5 = 4'b0101,
    state_6 = 4'b0110,  state_7 = 4'b0111,  state_8 = 4'b1000,
    state_9 = 4'b1001,  state_10= 4'b1010,  state_11= 4'b1011; 


    // 采样机
    always @(posedge clk_sample, posedge rst) begin
        if(rst) begin
            serial_arrival <= 1'b0;
            cnt_sample <= 4'b0;
            signal_sample <= 1'b0;
        end
        else begin
            // 在空闲状态寻找起始位
            if(current_state == state_0) begin
                case (serial_in)
                    1'b0 :  begin  // 出现低电平
                        // 8进制计数
                        if(cnt_sample == 4'b0111) begin
                            cnt_sample <= 4'b0;
                            serial_arrival <= 1'b1;
                        end
                        else begin
                            cnt_sample <= cnt_sample + 4'b1;
                        end
                    end
                    default : cnt_sample <= 4'b0;
                endcase
            end
            // 在接收状态对信号采样
            else begin
                serial_arrival <= 1'b0;
                // 16进制计数
                 if(cnt_sample == 4'b1111) begin
                    signal_sample <= serial_in;
                    cnt_sample <= 4'b0;
                 end
                 else begin
                     cnt_sample <= cnt_sample + 4'b1;
                 end   
            end 
        end
        
    end

////////////////////////接收状态机(三段式)///////////////////////////


    // 时序逻辑部分（当前状态）
    always @(posedge clk_baud, posedge rst) begin
        if(rst) begin
            current_state <= state_0; 
        end
        else begin
            current_state <= next_state;
        end    
    end


    // 组合逻辑部分（状态转换）
    always @(*) begin
        next_state = state_0;
        case (current_state)
            state_0 : begin
                    if (serial_arrival) begin
                        next_state <= state_1;
                    end
                    else 
                        next_state <= state_0;
                    end
            state_1 : begin  // 接收第一位
                    next_state = state_2;
                    end
            state_2 : begin
                    next_state = state_3;
                    end
            state_3 : begin
                    next_state = state_4;
                    end
            state_4 : begin
                    next_state = state_5;
                    end
            state_5 : begin
                    next_state = state_6;
                    end
            state_6 : begin
                    next_state = state_7;
                    end
            state_7 : begin
                    next_state = state_8;
                    end
            state_8 : begin
                    next_state = state_9;
                    end
            state_9 : begin 
                    next_state = state_10;
                    end
            state_10 : begin 
                    next_state = state_11;
                    end 
            state_11 : begin
                    next_state = state_0;
                    end        
            default: next_state = state_0;
        endcase    
    end


    // 组合逻辑部分（输出）
    always @(*) begin
        if(rst) 
            bus_out = 8'b0;
        else begin
            case (current_state) 
                state_0 : begin 
                          bus_buff = 9'b0;
                          bus_out = 8'b0;
                end
                state_1 : bus_buff[8] = signal_sample;
                state_2 : bus_buff[7] = signal_sample;
                state_3 : bus_buff[6] = signal_sample;
                state_4 : bus_buff[5] = signal_sample;
                state_5 : bus_buff[4] = signal_sample;
                state_6 : bus_buff[3] = signal_sample;
                state_7 : bus_buff[2] = signal_sample;
                state_8 : bus_buff[1] = signal_sample;
                state_9 : bus_buff[0] = signal_sample;
                state_10: begin  // 数据校验
                          if(bus_buff[0] != ^bus_buff[8:1])
                                bus_buff = 9'b0;
                          end
                state_11: bus_out = bus_buff[8:1];
                default: current_state = state_0;
            endcase
        end
                
    end
 
/////////////////////////////////////////////////////////////////
endmodule

UART/UART_vsc_state/uart_tx.v
// Moore型三段式状态机实现uart发送模块
/*
一帧bus_in数据的存在时间必须不小于一个clk_baud周期,且不大于12个clk_baud周期才能正确传输。

clk_baud:_/ 1\__/ 2\__/ 3\__······__/11\__/12\__/13\_
bus_in:  _/xx/¯¯¯¯¯¯¯¯¯¯¯¯¯¯······¯¯¯¯¯¯¯¯¯¯¯\xxxx\__

过短时，状态机无法进入下一状态去发送数据；过长时，状态机会重复发送这一帧数据。
可以通过修改bus_arrival参数的生成逻辑来解决，这里忽略这个问题。
*/
module uart_tx_moore (
    input rst,  // 异步复位信号（高电平有效）
    input clk_baud,  // 波特率时钟
    input [7:0] bus_in,  // 输入总线
    output reg serial_out  // 串行输出
);

    // 状态寄存器
    reg [3:0] current_state;  // 当前状态
    reg [3:0] next_state;  // 下一状态
    // 数据寄存器
    reg [7:0] bus_buff;
    reg parity_even;

    wire bus_arrival;

    // 状态码
    localparam 
    state_0 = 4'b0000,  state_1 = 4'b0001,  state_2 = 4'b0010,
    state_3 = 4'b0011,  state_4 = 4'b0100,  state_5 = 4'b0101,
    state_6 = 4'b0110,  state_7 = 4'b0111,  state_8 = 4'b1000,
    state_9 = 4'b1001,  state_10= 4'b1010,  state_11= 4'b1011; 


    // 如何判断总线数据到来？
    // 我的思路是非全零时表示总线数据到来
    assign bus_arrival = | bus_in;
    always @(*) begin
        if (rst)  
            bus_buff = 8'b0;
        else begin
            // 在空闲状态获取总线数据，
            if(current_state == state_0) begin
                if(bus_arrival)  begin
                    bus_buff = bus_in;                  
                    parity_even = ^ bus_buff;  // 偶校验
                end 
                else begin
                    bus_buff = 8'b0;
                    parity_even = 1'b0;
                end
            end
            // 在其他状态保持缓存的总线数据，不需要else语句
        end
    end

////////////////////////三段式状态机///////////////////////////


    // 时序逻辑部分（当前状态）
    always @(posedge clk_baud, posedge rst) begin
        if(rst) begin
            current_state <= state_0; 
        end
        else begin
            current_state <= next_state;
        end    
    end


    // 组合逻辑部分（状态转换）
    always @(*) begin
        next_state = state_0;
        case (current_state)
            state_0 : begin  // 等待状态
                    if(bus_arrival) 
                        next_state = state_1;
                    else
                        next_state = state_0;
                    end
            state_1 : begin  // 起始位发送状态
                    next_state = state_2;
                    end
            state_2 : begin
                    next_state = state_3;
                    end
            state_3 : begin
                    next_state = state_4;
                    end
            state_4 : begin
                    next_state = state_5;
                    end
            state_5 : begin
                    next_state = state_6;
                    end
            state_6 : begin
                    next_state = state_7;
                    end
            state_7 : begin
                    next_state = state_8;
                    end
            state_8 : begin
                    next_state = state_9;
                    end
            state_9 : begin
                    next_state = state_10;
                    end
            state_10 : begin
                    next_state = state_11;
                    end
            state_11 : begin
                    next_state = state_0;
                    end        
            default: next_state = state_0;
        endcase    
    end


    // 组合逻辑部分（输出）
    always @(*) begin
        if(rst) 
            serial_out = 1'b1;
        else begin
            case (current_state) 
                state_0 : serial_out = 1'b1;
                state_1 : serial_out = 1'b0;
                state_2 : serial_out = bus_buff[7];
                state_3 : serial_out = bus_buff[6];
                state_4 : serial_out = bus_buff[5];
                state_5 : serial_out = bus_buff[4];
                state_6 : serial_out = bus_buff[3];
                state_7 : serial_out = bus_buff[2];
                state_8 : serial_out = bus_buff[1];
                state_9 : serial_out = bus_buff[0];
                state_10: serial_out = parity_even;
                state_11: serial_out = 1'b1;
                default: serial_out = 1'b1;
            endcase
        end
                
    end

///////////////////////////////////////////////////////////////

endmodule

UART/UART_vsc_state/uart_baud.v

module uart_baud (
    input clk,  // 100MHz,T = 10ns
    output reg clk_baud,  // 波特率115200,T = 8680ns
    output reg clk_baud_sample );  // 115200*16 = 1843200,T = 540ns

    // 计数寄存器
    reg [9:0] cnt_clk_baud;
    reg [5:0] cnt_clk_sample;

    //初始化
    initial begin
        clk_baud <= 1'b1;
        clk_baud_sample <= 1'b1;
        cnt_clk_baud <= 10'b0;
        cnt_clk_sample <= 6'b0;
    end

    localparam change1 = 10'b 01_1011_0010,
                restart1 = 10'b 11_0110_0100,
                chagne2 = 6'b 01_1011,
                restart2 = 6'b 11_0110;


    always @(posedge clk) begin
        case (cnt_clk_baud)
           change1 : begin
               clk_baud <= ~clk_baud;  // 占空比50%
               cnt_clk_baud <= cnt_clk_baud + 1;
           end
           restart1 : begin
                clk_baud <= ~clk_baud;
                cnt_clk_baud <= 0;
           end
            default: cnt_clk_baud <= cnt_clk_baud + 1;
        endcase 
    end


    always @(posedge clk) begin
        case (cnt_clk_sample)
           chagne2 : begin
               clk_baud_sample <= ~clk_baud_sample;  // 占空比50%
               cnt_clk_sample <= cnt_clk_sample + 1;
           end
           restart2 : begin
                clk_baud_sample <= ~clk_baud_sample;
                cnt_clk_sample <= 0;
           end
            default: cnt_clk_sample <= cnt_clk_sample + 1;
        endcase 
    end

endmodule

UART/UART_vsc_state/uart.v
`timescale 10ns/1ns
`include "uart_baud.v"
`include "uart_tx.v"
`include "uart_rx.v"

module UART (
    input clk,
    input rst,
    input rx_in,
    output tx_out,
    output [7:0] bus_out,
    input [7:0] bus_in );


    //中间连线
    wire clk_baud;
    wire clk_baud_sample;


    //波特时钟实例化
    uart_baud     uart_baud_ins (
        .clk             (clk),
        .clk_baud        (clk_baud),
        .clk_baud_sample (clk_baud_sample) );


    uart_tx_moore        uart_tx_ins (
        .clk_baud    (clk_baud),
        .rst         (rst),
        .bus_in      (bus_in),
        .serial_out      (tx_out) );


    // 接收模块实例化
    uart_rx_moore        uart_rx_ins (
        .clk_baud     (clk_baud),
        .clk_sample   (clk_baud_sample),
        .rst          (rst),
        .serial_in    (rx_in),
        .bus_out      (bus_out) );


endmodule

UART/UART_vsc_state/tb_uart.v
`timescale 1ns/1ps
`include "uart.v"
 
 // 回环测试

 module tb_uart_loopback ();

    reg [7:0] bus_in;
    reg clk;

    wire [7:0] bus_out;
    wire tx_out;

    // 
    initial begin
        bus_in <= 8'b0;
        clk <= 1'b1;
    end

    // 时钟，T=10ns
    initial begin
        repeat(100000)
     #5 clk <= ~clk;
    end

    // 输入数据
    initial begin
                    bus_in <= 8'b0;  // 5个波特周期空闲
        #(8680*5)   bus_in <= 8'b0101_0101;  // 2个波特周期输入
        #(8680*2)    bus_in <= 8'b0; 
    end

    // 发送
    UART      tb_UART_tx (
    .clk        (clk),
    //.model      (1'b0),
    .rst        (1'b0),
    .bus_in     (bus_in),
    .tx_out     (tx_out));


    // 接收
    UART      tb_UART_rx (
    .clk        (clk),
    //.model      (1'b1),
    .rst        (1'b0),
    .rx_in      (tx_out),
    .bus_out    (bus_out) );

    initial begin
        $dumpfile("wave_uart.vcd");
        $dumpvars(0,tb_uart_loopback);
    end
 
 endmodule

UART/UART_vsc_state/wave_uart.vcd
$date
	Wed Jun 15 21:09:38 2022
$end
$version
	Icarus Verilog
$end
$timescale
	1ns
$end
$scope module tb_uart_loopback $end
$var wire 1 ! tx_out $end
$var wire 8 " bus_out [7:0] $end
$var reg 8 # bus_in [7:0] $end
$var reg 1 $ clk $end
$scope module tb_UART_rx $end
$var wire 8 % bus_in [7:0] $end
$var wire 1 $ clk $end
$var wire 1 & rst $end
$var wire 1 ' tx_out $end
$var wire 1 ! rx_in $end
$var wire 1 ( clk_baud_sample $end
$var wire 1 ) clk_baud $end
$var wire 8 * bus_out [7:0] $end
$scope module uart_baud_ins $end
$var wire 1 $ clk $end
$var reg 1 ) clk_baud $end
$var reg 1 ( clk_baud_sample $end
$var reg 10 + cnt_clk_baud [9:0] $end
$var reg 6 , cnt_clk_sample [5:0] $end
$upscope $end
$scope module uart_rx_ins $end
$var wire 1 ) clk_baud $end
$var wire 1 ( clk_sample $end
$var wire 1 & rst $end
$var wire 1 ! serial_in $end
$var reg 9 - bus_buff [8:0] $end
$var reg 8 . bus_out [7:0] $end
$var reg 4 / cnt_sample [3:0] $end
$var reg 4 0 current_state [3:0] $end
$var reg 4 1 next_state [3:0] $end
$var reg 1 2 serial_arrival $end
$var reg 1 3 signal_sample $end
$upscope $end
$scope module uart_tx_ins $end
$var wire 8 4 bus_in [7:0] $end
$var wire 1 ) clk_baud $end
$var wire 1 & rst $end
$var wire 1 5 bus_arrival $end
$var reg 8 6 bus_buff [7:0] $end
$var reg 4 7 current_state [3:0] $end
$var reg 4 8 next_state [3:0] $end
$var reg 1 9 parity_even $end
$var reg 1 ' serial_out $end
$upscope $end
$upscope $end
$scope module tb_UART_tx $end
$var wire 8 : bus_in [7:0] $end
$var wire 1 $ clk $end
$var wire 1 ; rst $end
$var wire 1 < rx_in $end
$var wire 1 ! tx_out $end
$var wire 1 = clk_baud_sample $end
$var wire 1 > clk_baud $end
$var wire 8 ? bus_out [7:0] $end
$scope module uart_baud_ins $end
$var wire 1 $ clk $end
$var reg 1 > clk_baud $end
$var reg 1 = clk_baud_sample $end
$var reg 10 @ cnt_clk_baud [9:0] $end
$var reg 6 A cnt_clk_sample [5:0] $end
$upscope $end
$scope module uart_rx_ins $end
$var wire 1 > clk_baud $end
$var wire 1 = clk_sample $end
$var wire 1 ; rst $end
$var wire 1 < serial_in $end
$var reg 9 B bus_buff [8:0] $end
$var reg 8 C bus_out [7:0] $end
$var reg 4 D cnt_sample [3:0] $end
$var reg 4 E current_state [3:0] $end
$var reg 4 F next_state [3:0] $end
$var reg 1 G serial_arrival $end
$var reg 1 H signal_sample $end
$upscope $end
$scope module uart_tx_ins $end
$var wire 8 I bus_in [7:0] $end
$var wire 1 > clk_baud $end
$var wire 1 ; rst $end
$var wire 1 J bus_arrival $end
$var reg 8 K bus_buff [7:0] $end
$var reg 4 L current_state [3:0] $end
$var reg 4 M next_state [3:0] $end
$var reg 1 N parity_even $end
$var reg 1 ! serial_out $end
$upscope $end
$upscope $end
$upscope $end
$enddefinitions $end
#0
$dumpvars
xN
b0 M
bx L
bx K
0J
b0 I
xH
xG
b0 F
b0 E
b0 D
bx C
bx B
b1 A
b1 @
bx ?
1>
1=
z<
0;
b0 :
x9
bx 8
bx 7
bx 6
x5
bz 4
x3
x2
b0 1
b0 0
b0 /
bx .
bx -
b1 ,
b1 +
bx *
1)
1(
1'
0&
bz %
1$
b0 #
bx "
1!
$end
#50
0$
#100
b10 ,
b10 +
b10 A
b10 @
1$
#150
0$
#200
b11 @
b11 A
b11 +
b11 ,
1$
#250
0$
#300
b100 ,
b100 +
b100 A
b100 @
1$
#350
0$
#400
b101 @
b101 A
b101 +
b101 ,
1$
#450
0$
#500
b110 ,
b110 +
b110 A
b110 @
1$
#550
0$
#600
b111 @
b111 A
b111 +
b111 ,
1$
#650
0$
#700
b1000 ,
b1000 +
b1000 A
b1000 @
1$
#750
0$
#800
b1001 @
b1001 A
b1001 +
b1001 ,
1$
#850
0$
#900
b1010 ,
b1010 +
b1010 A
b1010 @
1$
#950
0$
#1000
b1011 @
b1011 A
b1011 +
b1011 ,
1$
#1050
0$
#1100
b1100 ,
b1100 +
b1100 A
b1100 @
1$
#1150
0$
#1200
b1101 @
b1101 A
b1101 +
b1101 ,
1$
#1250
0$
#1300
b1110 ,
b1110 +
b1110 A
b1110 @
1$
#1350
0$
#1400
b1111 @
b1111 A
b1111 +
b1111 ,
1$
#1450
0$
#1500
b10000 ,
b10000 +
b10000 A
b10000 @
1$
#1550
0$
#1600
b10001 @
b10001 A
b10001 +
b10001 ,
1$
#1650
0$
#1700
b10010 ,
b10010 +
b10010 A
b10010 @
1$
#1750
0$
#1800
b10011 @
b10011 A
b10011 +
b10011 ,
1$
#1850
0$
#1900
b10100 ,
b10100 +
b10100 A
b10100 @
1$
#1950
0$
#2000
b10101 @
b10101 A
b10101 +
b10101 ,
1$
#2050
0$
#2100
b10110 ,
b10110 +
b10110 A
b10110 @
1$
#2150
0$
#2200
b10111 @
b10111 A
b10111 +
b10111 ,
1$
#2250
0$
#2300
b11000 ,
b11000 +
b11000 A
b11000 @
1$
#2350
0$
#2400
b11001 @
b11001 A
b11001 +
b11001 ,
1$
#2450
0$
#2500
b11010 ,
b11010 +
b11010 A
b11010 @
1$
#2550
0$
#2600
b11011 @
b11011 A
b11011 +
b11011 ,
1$
#2650
0$
#2700
b11100 ,
0(
b11100 +
b11100 A
0=
b11100 @
1$
#2750
0$
#2800
b11101 @
b11101 A
b11101 +
b11101 ,
1$
#2850
0$
#2900
b11110 ,
b11110 +
b11110 A
b11110 @
1$
#2950
0$
#3000
b11111 @
b11111 A
b11111 +
b11111 ,
1$
#3050
0$
#3100
b100000 ,
b100000 +
b100000 A
b100000 @
1$
#3150
0$
#3200
b100001 @
b100001 A
b100001 +
b100001 ,
1$
#3250
0$
#3300
b100010 ,
b100010 +
b100010 A
b100010 @
1$
#3350
0$
#3400
b100011 @
b100011 A
b100011 +
b100011 ,
1$
#3450
0$
#3500
b100100 ,
b100100 +
b100100 A
b100100 @
1$
#3550
0$
#3600
b100101 @
b100101 A
b100101 +
b100101 ,
1$
#3650
0$
#3700
b100110 ,
b100110 +
b100110 A
b100110 @
1$
#3750
0$
#3800
b100111 @
b100111 A
b100111 +
b100111 ,
1$
#3850
0$
#3900
b101000 ,
b101000 +
b101000 A
b101000 @
1$
#3950
0$
#4000
b101001 @
b101001 A
b101001 +
b101001 ,
1$
#4050
0$
#4100
b101010 ,
b101010 +
b101010 A
b101010 @
1$
#4150
0$
#4200
b101011 @
b101011 A
b101011 +
b101011 ,
1$
#4250
0$
#4300
b101100 ,
b101100 +
b101100 A
b101100 @
1$
#4350
0$
#4400
b101101 @
b101101 A
b101101 +
b101101 ,
1$
#4450
0$
#4500
b101110 ,
b101110 +
b101110 A
b101110 @
1$
#4550
0$
#4600
b101111 @
b101111 A
b101111 +
b101111 ,
1$
#4650
0$
#4700
b110000 ,
b110000 +
b110000 A
b110000 @
1$
#4750
0$
#4800
b110001 @
b110001 A
b110001 +
b110001 ,
1$
#4850
0$
#4900
b110010 ,
b110010 +
b110010 A
b110010 @
1$
#4950
0$
#5000
b110011 @
b110011 A
b110011 +
b110011 ,
1$
#5050
0$
#5100
b110100 ,
b110100 +
b110100 A
b110100 @
1$
#5150
0$
#5200
b110101 @
b110101 A
b110101 +
b110101 ,
1$
#5250
0$
#5300
b110110 ,
b110110 +
b110110 A
b110110 @
1$
#5350
0$
#5400
b110111 @
b0 A
1=
b110111 +
b0 ,
1(
1$
#5450
0$
#5500
b1 ,
b111000 +
b1 A
b111000 @
1$
#5550
0$
#5600
b111001 @
b10 A
b111001 +
b10 ,
1$
#5650
0$
#5700
b11 ,
b111010 +
b11 A
b111010 @
1$
#5750
0$
#5800
b111011 @
b100 A
b111011 +
b100 ,
1$
#5850
0$
#5900
b101 ,
b111100 +
b101 A
b111100 @
1$
#5950
0$
#6000
b111101 @
b110 A
b111101 +
b110 ,
1$
#6050
0$
#6100
b111 ,
b111110 +
b111 A
b111110 @
1$
#6150
0$
#6200
b111111 @
b1000 A
b111111 +
b1000 ,
1$
#6250
0$
#6300
b1001 ,
b1000000 +
b1001 A
b1000000 @
1$
#6350
0$
#6400
b1000001 @
b1010 A
b1000001 +
b1010 ,
1$
#6450
0$
#6500
b1011 ,
b1000010 +
b1011 A
b1000010 @
1$
#6550
0$
#6600
b1000011 @
b1100 A
b1000011 +
b1100 ,
1$
#6650
0$
#6700
b1101 ,
b1000100 +
b1101 A
b1000100 @
1$
#6750
0$
#6800
b1000101 @
b1110 A
b1000101 +
b1110 ,
1$
#6850
0$
#6900
b1111 ,
b1000110 +
b1111 A
b1000110 @
1$
#6950
0$
#7000
b1000111 @
b10000 A
b1000111 +
b10000 ,
1$
#7050
0$
#7100
b10001 ,
b1001000 +
b10001 A
b1001000 @
1$
#7150
0$
#7200
b1001001 @
b10010 A
b1001001 +
b10010 ,
1$
#7250
0$
#7300
b10011 ,
b1001010 +
b10011 A
b1001010 @
1$
#7350
0$
#7400
b1001011 @
b10100 A
b1001011 +
b10100 ,
1$
#7450
0$
#7500
b10101 ,
b1001100 +
b10101 A
b1001100 @
1$
#7550
0$
#7600
b1001101 @
b10110 A
b1001101 +
b10110 ,
1$
#7650
0$
#7700
b10111 ,
b1001110 +
b10111 A
b1001110 @
1$
#7750
0$
#7800
b1001111 @
b11000 A
b1001111 +
b11000 ,
1$
#7850
0$
#7900
b11001 ,
b1010000 +
b11001 A
b1010000 @
1$
#7950
0$
#8000
b1010001 @
b11010 A
b1010001 +
b11010 ,
1$
#8050
0$
#8100
b11011 ,
b1010010 +
b11011 A
b1010010 @
1$
#8150
0$
#8200
b1010011 @
b11100 A
0=
b1010011 +
b11100 ,
0(
1$
#8250
0$
#8300
b11101 ,
b1010100 +
b11101 A
b1010100 @
1$
#8350
0$
#8400
b1010101 @
b11110 A
b1010101 +
b11110 ,
1$
#8450
0$
#8500
b11111 ,
b1010110 +
b11111 A
b1010110 @
1$
#8550
0$
#8600
b1010111 @
b100000 A
b1010111 +
b100000 ,
1$
#8650
0$
#8700
b100001 ,
b1011000 +
b100001 A
b1011000 @
1$
#8750
0$
#8800
b1011001 @
b100010 A
b1011001 +
b100010 ,
1$
#8850
0$
#8900
b100011 ,
b1011010 +
b100011 A
b1011010 @
1$
#8950
0$
#9000
b1011011 @
b100100 A
b1011011 +
b100100 ,
1$
#9050
0$
#9100
b100101 ,
b1011100 +
b100101 A
b1011100 @
1$
#9150
0$
#9200
b1011101 @
b100110 A
b1011101 +
b100110 ,
1$
#9250
0$
#9300
b100111 ,
b1011110 +
b100111 A
b1011110 @
1$
#9350
0$
#9400
b1011111 @
b101000 A
b1011111 +
b101000 ,
1$
#9450
0$
#9500
b101001 ,
b1100000 +
b101001 A
b1100000 @
1$
#9550
0$
#9600
b1100001 @
b101010 A
b1100001 +
b101010 ,
1$
#9650
0$
#9700
b101011 ,
b1100010 +
b101011 A
b1100010 @
1$
#9750
0$
#9800
b1100011 @
b101100 A
b1100011 +
b101100 ,
1$
#9850
0$
#9900
b101101 ,
b1100100 +
b101101 A
b1100100 @
1$
#9950
0$
#10000
b1100101 @
b101110 A
b1100101 +
b101110 ,
1$
#10050
0$
#10100
b101111 ,
b1100110 +
b101111 A
b1100110 @
1$
#10150
0$
#10200
b1100111 @
b110000 A
b1100111 +
b110000 ,
1$
#10250
0$
#10300
b110001 ,
b1101000 +
b110001 A
b1101000 @
1$
#10350
0$
#10400
b1101001 @
b110010 A
b1101001 +
b110010 ,
1$
#10450
0$
#10500
b110011 ,
b1101010 +
b110011 A
b1101010 @
1$
#10550
0$
#10600
b1101011 @
b110100 A
b1101011 +
b110100 ,
1$
#10650
0$
#10700
b110101 ,
b1101100 +
b110101 A
b1101100 @
1$
#10750
0$
#10800
b1101101 @
b110110 A
b1101101 +
b110110 ,
1$
#10850
0$
#10900
b0 ,
1(
b1101110 +
b0 A
1=
b1101110 @
1$
#10950
0$
#11000
b1101111 @
b1 A
b1101111 +
b1 ,
1$
#11050
0$
#11100
b10 ,
b1110000 +
b10 A
b1110000 @
1$
#11150
0$
#11200
b1110001 @
b11 A
b1110001 +
b11 ,
1$
#11250
0$
#11300
b100 ,
b1110010 +
b100 A
b1110010 @
1$
#11350
0$
#11400
b1110011 @
b101 A
b1110011 +
b101 ,
1$
#11450
0$
#11500
b110 ,
b1110100 +
b110 A
b1110100 @
1$
#11550
0$
#11600
b1110101 @
b111 A
b1110101 +
b111 ,
1$
#11650
0$
#11700
b1000 ,
b1110110 +
b1000 A
b1110110 @
1$
#11750
0$
#11800
b1110111 @
b1001 A
b1110111 +
b1001 ,
1$
#11850
0$
#11900
b1010 ,
b1111000 +
b1010 A
b1111000 @
1$
#11950
0$
#12000
b1111001 @
b1011 A
b1111001 +
b1011 ,
1$
#12050
0$
#12100
b1100 ,
b1111010 +
b1100 A
b1111010 @
1$
#12150
0$
#12200
b1111011 @
b1101 A
b1111011 +
b1101 ,
1$
#12250
0$
#12300
b1110 ,
b1111100 +
b1110 A
b1111100 @
1$
#12350
0$
#12400
b1111101 @
b1111 A
b1111101 +
b1111 ,
1$
#12450
0$
#12500
b10000 ,
b1111110 +
b10000 A
b1111110 @
1$
#12550
0$
#12600
b1111111 @
b10001 A
b1111111 +
b10001 ,
1$
#12650
0$
#12700
b10010 ,
b10000000 +
b10010 A
b10000000 @
1$
#12750
0$
#12800
b10000001 @
b10011 A
b10000001 +
b10011 ,
1$
#12850
0$
#12900
b10100 ,
b10000010 +
b10100 A
b10000010 @
1$
#12950
0$
#13000
b10000011 @
b10101 A
b10000011 +
b10101 ,
1$
#13050
0$
#13100
b10110 ,
b10000100 +
b10110 A
b10000100 @
1$
#13150
0$
#13200
b10000101 @
b10111 A
b10000101 +
b10111 ,
1$
#13250
0$
#13300
b11000 ,
b10000110 +
b11000 A
b10000110 @
1$
#13350
0$
#13400
b10000111 @
b11001 A
b10000111 +
b11001 ,
1$
#13450
0$
#13500
b11010 ,
b10001000 +
b11010 A
b10001000 @
1$
#13550
0$
#13600
b10001001 @
b11011 A
b10001001 +
b11011 ,
1$
#13650
0$
#13700
b11100 ,
0(
b10001010 +
b11100 A
0=
b10001010 @
1$
#13750
0$
#13800
b10001011 @
b11101 A
b10001011 +
b11101 ,
1$
#13850
0$
#13900
b11110 ,
b10001100 +
b11110 A
b10001100 @
1$
#13950
0$
#14000
b10001101 @
b11111 A
b10001101 +
b11111 ,
1$
#14050
0$
#14100
b100000 ,
b10001110 +
b100000 A
b10001110 @
1$
#14150
0$
#14200
b10001111 @
b100001 A
b10001111 +
b100001 ,
1$
#14250
0$
#14300
b100010 ,
b10010000 +
b100010 A
b10010000 @
1$
#14350
0$
#14400
b10010001 @
b100011 A
b10010001 +
b100011 ,
1$
#14450
0$
#14500
b100100 ,
b10010010 +
b100100 A
b10010010 @
1$
#14550
0$
#14600
b10010011 @
b100101 A
b10010011 +
b100101 ,
1$
#14650
0$
#14700
b100110 ,
b10010100 +
b100110 A
b10010100 @
1$
#14750
0$
#14800
b10010101 @
b100111 A
b10010101 +
b100111 ,
1$
#14850
0$
#14900
b101000 ,
b10010110 +
b101000 A
b10010110 @
1$
#14950
0$
#15000
b10010111 @
b101001 A
b10010111 +
b101001 ,
1$
#15050
0$
#15100
b101010 ,
b10011000 +
b101010 A
b10011000 @
1$
#15150
0$
#15200
b10011001 @
b101011 A
b10011001 +
b101011 ,
1$
#15250
0$
#15300
b101100 ,
b10011010 +
b101100 A
b10011010 @
1$
#15350
0$
#15400
b10011011 @
b101101 A
b10011011 +
b101101 ,
1$
#15450
0$
#15500
b101110 ,
b10011100 +
b101110 A
b10011100 @
1$
#15550
0$
#15600
b10011101 @
b101111 A
b10011101 +
b101111 ,
1$
#15650
0$
#15700
b110000 ,
b10011110 +
b110000 A
b10011110 @
1$
#15750
0$
#15800
b10011111 @
b110001 A
b10011111 +
b110001 ,
1$
#15850
0$
#15900
b110010 ,
b10100000 +
b110010 A
b10100000 @
1$
#15950
0$
#16000
b10100001 @
b110011 A
b10100001 +
b110011 ,
1$
#16050
0$
#16100
b110100 ,
b10100010 +
b110100 A
b10100010 @
1$
#16150
0$
#16200
b10100011 @
b110101 A
b10100011 +
b110101 ,
1$
#16250
0$
#16300
b110110 ,
b10100100 +
b110110 A
b10100100 @
1$
#16350
0$
#16400
b10100101 @
b0 A
1=
b10100101 +
b0 ,
1(
1$
#16450
0$
#16500
b1 ,
b10100110 +
b1 A
b10100110 @
1$
#16550
0$
#16600
b10100111 @
b10 A
b10100111 +
b10 ,
1$
#16650
0$
#16700
b11 ,
b10101000 +
b11 A
b10101000 @
1$
#16750
0$
#16800
b10101001 @
b100 A
b10101001 +
b100 ,
1$
#16850
0$
#16900
b101 ,
b10101010 +
b101 A
b10101010 @
1$
#16950
0$
#17000
b10101011 @
b110 A
b10101011 +
b110 ,
1$
#17050
0$
#17100
b111 ,
b10101100 +
b111 A
b10101100 @
1$
#17150
0$
#17200
b10101101 @
b1000 A
b10101101 +
b1000 ,
1$
#17250
0$
#17300
b1001 ,
b10101110 +
b1001 A
b10101110 @
1$
#17350
0$
#17400
b10101111 @
b1010 A
b10101111 +
b1010 ,
1$
#17450
0$
#17500
b1011 ,
b10110000 +
b1011 A
b10110000 @
1$
#17550
0$
#17600
b10110001 @
b1100 A
b10110001 +
b1100 ,
1$
#17650
0$
#17700
b1101 ,
b10110010 +
b1101 A
b10110010 @
1$
#17750
0$
#17800
b10110011 @
b1110 A
b10110011 +
b1110 ,
1$
#17850
0$
#17900
b1111 ,
b10110100 +
b1111 A
b10110100 @
1$
#17950
0$
#18000
b10110101 @
b10000 A
b10110101 +
b10000 ,
1$
#18050
0$
#18100
b10001 ,
b10110110 +
b10001 A
b10110110 @
1$
#18150
0$
#18200
b10110111 @
b10010 A
b10110111 +
b10010 ,
1$
#18250
0$
#18300
b10011 ,
b10111000 +
b10011 A
b10111000 @
1$
#18350
0$
#18400
b10111001 @
b10100 A
b10111001 +
b10100 ,
1$
#18450
0$
#18500
b10101 ,
b10111010 +
b10101 A
b10111010 @
1$
#18550
0$
#18600
b10111011 @
b10110 A
b10111011 +
b10110 ,
1$
#18650
0$
#18700
b10111 ,
b10111100 +
b10111 A
b10111100 @
1$
#18750
0$
#18800
b10111101 @
b11000 A
b10111101 +
b11000 ,
1$
#18850
0$
#18900
b11001 ,
b10111110 +
b11001 A
b10111110 @
1$
#18950
0$
#19000
b10111111 @
b11010 A
b10111111 +
b11010 ,
1$
#19050
0$
#19100
b11011 ,
b11000000 +
b11011 A
b11000000 @
1$
#19150
0$
#19200
b11000001 @
b11100 A
0=
b11000001 +
b11100 ,
0(
1$
#19250
0$
#19300
b11101 ,
b11000010 +
b11101 A
b11000010 @
1$
#19350
0$
#19400
b11000011 @
b11110 A
b11000011 +
b11110 ,
1$
#19450
0$
#19500
b11111 ,
b11000100 +
b11111 A
b11000100 @
1$
#19550
0$
#19600
b11000101 @
b100000 A
b11000101 +
b100000 ,
1$
#19650
0$
#19700
b100001 ,
b11000110 +
b100001 A
b11000110 @
1$
#19750
0$
#19800
b11000111 @
b100010 A
b11000111 +
b100010 ,
1$
#19850
0$
#19900
b100011 ,
b11001000 +
b100011 A
b11001000 @
1$
#19950
0$
#20000
b11001001 @
b100100 A
b11001001 +
b100100 ,
1$
#20050
0$
#20100
b100101 ,
b11001010 +
b100101 A
b11001010 @
1$
#20150
0$
#20200
b11001011 @
b100110 A
b11001011 +
b100110 ,
1$
#20250
0$
